{
    "key": "group_60903847bf245",
    "title": "Block - Cover White Box",
    "fields": [
        {
            "key": "field_60903858e2338",
            "label": "Image",
            "name": "wd_cwb_block_image",
            "type": "image",
            "instructions": "",
            "required": 1,
            "conditional_logic": 0,
            "wrapper": {
                "width": "",
                "class": "",
                "id": ""
            },
            "return_format": "array",
            "preview_size": "full",
            "library": "all",
            "min_width": "",
            "min_height": "",
            "min_size": "",
            "max_width": "",
            "max_height": "",
            "max_size": "",
            "mime_types": ""
        },
        {
            "key": "field_6090386fe2339",
            "label": "Content Vertical Alignment",
            "name": "wd_cwb_block_content_vertical_alignment",
            "type": "button_group",
            "instructions": "",
            "required": 1,
            "conditional_logic": 0,
            "wrapper": {
                "width": "",
                "class": "",
                "id": ""
            },
            "choices": {
                "top-align": "Top",
                "center-align": "Middle",
                "bottom-align": "Bottom"
            },
            "allow_null": 0,
            "default_value": "",
            "layout": "horizontal",
            "return_format": "value"
        },
        {
            "key": "field_609038a2e233a",
            "label": "Content Horizontal Alignment",
            "name": "wd_cwb_block_content_horizontal_alignment",
            "type": "button_group",
            "instructions": "",
            "required": 1,
            "conditional_logic": 0,
            "wrapper": {
                "width": "",
                "class": "",
                "id": ""
            },
            "choices": {
                "left-align": "Left",
                "center-align": "Middle",
                "right-align": "Right"
            },
            "allow_null": 0,
            "default_value": "",
            "layout": "horizontal",
            "return_format": "value"
        }
    ],
    "location": [
        [
            {
                "param": "block",
                "operator": "==",
                "value": "acf\/acf-cover-with-white-box"
            }
        ]
    ],
    "menu_order": 0,
    "position": "normal",
    "style": "default",
    "label_placement": "top",
    "instruction_placement": "label",
    "hide_on_screen": "",
    "active": true,
    "description": "",
    "modified": 1620411486
}